optimum/quanto/__init__.py
optimum/quanto/calibrate.py
optimum/quanto/quantize.py
optimum/quanto/library/README.md
optimum/quanto/library/__init__.py
optimum/quanto/library/qbytes_mm.py
optimum/quanto/library/quantize.py
optimum/quanto/library/unpack.py
optimum/quanto/library/extensions/README.md
optimum/quanto/library/extensions/__init__.py
optimum/quanto/library/extensions/extension.py
optimum/quanto/library/extensions/cpp/README.md
optimum/quanto/library/extensions/cpp/__init__.py
optimum/quanto/library/extensions/cpp/pybind_module.cpp
optimum/quanto/library/extensions/cpp/unpack.cpp
optimum/quanto/library/extensions/cpp/unpack.h
optimum/quanto/library/extensions/cuda/README.md
optimum/quanto/library/extensions/cuda/__init__.py
optimum/quanto/library/extensions/cuda/pybind_module.cpp
optimum/quanto/library/extensions/cuda/unpack.cu
optimum/quanto/library/extensions/cuda/unpack.h
optimum/quanto/library/extensions/cuda/awq/dequantize.cuh
optimum/quanto/library/extensions/cuda/awq/v2/gemm_cuda.cu
optimum/quanto/library/extensions/cuda/awq/v2/gemm_cuda.h
optimum/quanto/library/extensions/cuda/awq/v2/gemv_cuda.cu
optimum/quanto/library/extensions/cuda/awq/v2/gemv_cuda.h
optimum/quanto/library/extensions/cuda/awq/v2/semaphore.h
optimum/quanto/library/extensions/cuda/marlin/COPYRIGHT
optimum/quanto/library/extensions/cuda/marlin/fp8_marlin.cu
optimum/quanto/library/extensions/cuda/marlin/fp8_marlin.cuh
optimum/quanto/library/extensions/cuda/marlin/gptq_marlin.cuh
optimum/quanto/library/extensions/cuda/marlin/gptq_marlin_dtypes.cuh
optimum/quanto/library/extensions/cuda/marlin/gptq_marlin_repack.cu
optimum/quanto/library/extensions/cuda/marlin/gptq_marlin_repack.cuh
optimum/quanto/library/extensions/cuda/marlin/marlin_cuda.cpp
optimum/quanto/library/extensions/cuda/marlin/marlin_cuda.h
optimum/quanto/library/extensions/cuda/marlin/marlin_cuda_kernel.cu
optimum/quanto/library/extensions/cuda/marlin/marlin_cuda_kernel.cuh
optimum/quanto/library/extensions/hip/__init__.py
optimum_quanto-0.2.6.dist-info/LICENSE
optimum_quanto-0.2.6.dist-info/METADATA
optimum_quanto-0.2.6.dist-info/WHEEL
optimum_quanto-0.2.6.dist-info/top_level.txt
optimum_quanto-0.2.6.dist-info/RECORD
