Metadata-Version: 2.1
Name: optimum-quanto
Version: 0.2.6
Summary: A pytorch quantization backend for optimum.
Author: David Corvoysier
Maintainer-email: "HuggingFace Inc. Special Ops Team" <hardware@huggingface.co>
License: Apache-2.0
Project-URL: homepage, https://github.com/huggingface/optimum-quanto
Keywords: torch,quantization
Classifier: Development Status :: 2 - Pre-Alpha
Classifier: License :: OSI Approved :: Apache Software License
Classifier: Intended Audience :: Developers
Classifier: Intended Audience :: Education
Classifier: Intended Audience :: Science/Research
Classifier: Operating System :: OS Independent
Classifier: Programming Language :: Python :: 3.9
Classifier: Programming Language :: Python :: 3.10
Classifier: Programming Language :: Python :: 3.11
Classifier: Topic :: Scientific/Engineering :: Artificial Intelligence
Requires-Python: >=3.9.0
License-File: LICENSE
Requires-Dist: torch >=2.4.0
Requires-Dist: ninja
Requires-Dist: numpy
Requires-Dist: safetensors
Requires-Dist: huggingface-hub
Provides-Extra: dev
Requires-Dist: pytest ; extra == 'dev'
Requires-Dist: ruff ; extra == 'dev'
Provides-Extra: examples
Requires-Dist: torchvision ; extra == 'examples'
Requires-Dist: transformers ; extra == 'examples'
Requires-Dist: diffusers ; extra == 'examples'
Requires-Dist: datasets ; extra == 'examples'
Requires-Dist: accelerate ; extra == 'examples'
Requires-Dist: sentencepiece ; extra == 'examples'
Requires-Dist: scipy ; extra == 'examples'
